pkgtool/__init__.py
pkgtool/version.py
pkgtool-0.1b55.data/scripts/pkgtool
pkgtool-0.1b55.dist-info/DESCRIPTION.rst
pkgtool-0.1b55.dist-info/METADATA
pkgtool-0.1b55.dist-info/RECORD
pkgtool-0.1b55.dist-info/WHEEL
pkgtool-0.1b55.dist-info/metadata.json
pkgtool-0.1b55.dist-info/top_level.txt
