Metadata-Version: 2.0
Name: pkgtool
Version: 0.1b55
Summary: python makefile system
Home-page: http://github.com/chuck1/pytool
Author: Charles Rymal
Author-email: charlesrymal@gmail.com
License: MIT
Platform: UNKNOWN
Requires-Dist: py (==1.4.34)
Requires-Dist: pytest (==3.1.2)
Requires-Dist: termcolor (==1.1.0)
Requires-Dist: toml (==0.9.2)
